{"name":"Burst Lightning","layout":"normal","manaCost":"{R}","cmc":1.0,"type":"Instant","rarity":"Common","text":"Kicker {4} (You may pay an additional {4} as you cast this spell.)\nBurst Lightning deals 2 damage to any target. If this spell was kicked, it deals 4 damage instead.","artist":"Vance Kovacs","number":"879","set":"MB1","setName":"Mystery Booster","id":"8603fae1-14fd-5d8f-80d0-2658b66ce3e5","supertypes":[],"subtypes":[],"types":["Instant"],"colors":["Red"],"colorIdentity":["R"],"printings":["MB1","MM2","P10","PLIST","PRM","ZEN"],"legalities":[{"format":"Commander","legality":"Legal"},{"format":"Duel","legality":"Legal"},{"format":"Legacy","legality":"Legal"},{"format":"Modern","legality":"Legal"},{"format":"Pauper","legality":"Legal"},{"format":"Penny","legality":"Legal"},{"format":"Vintage","legality":"Legal"}],"rulings":[],"foreignNames":[]}
